{
  "digest_version": 4,
  "source_export_version": 2,
  "source_fetched_at_local": "2026-07-02T17:38:46",
  "calendar": {
    "snapshot_end": "2026-07-02",
    "window_start": "2026-06-26",
    "window_end": "2026-07-02",
    "iso_week_current_monday": "2026-06-29",
    "iso_week_previous_monday": "2026-06-22"
  },
  "last_night": {
    "sleep": {
      "date": "2026-07-02",
      "sleep_time_seconds": 29400,
      "sleep_time_hours": 8.17,
      "deep_sleep_minutes": 119.0,
      "light_sleep_minutes": 267.0,
      "rem_sleep_minutes": 104.0,
      "awake_minutes": 1.0,
      "sleep_score": 95,
      "sleep_score_qualifier": "EXCELLENT",
      "avg_overnight_hrv": null,
      "avg_sleep_stress": 12.0
    },
    "hrv": {
      "date": "2026-07-02",
      "last_night_avg": 51,
      "last_night_5_min_high": 78,
      "weekly_avg": 48,
      "status": "BALANCED",
      "feedback_phrase": "HRV_BALANCED_5",
      "baseline_balanced_low": 37,
      "baseline_balanced_upper": 48
    },
    "cardio": {
      "date": "2026-07-02",
      "resting_heart_rate": 52,
      "resting_hr_7d_avg": 54,
      "max_heart_rate": 99,
      "max_avg_heart_rate": 95,
      "min_heart_rate": 48,
      "avg_respiration": 17.0
    },
    "body_battery": {
      "date": "2026-07-02",
      "at_wake_time": 100,
      "charged": 81,
      "drained": 22,
      "during_sleep": 81,
      "highest_value": 100,
      "lowest_value": 20,
      "most_recent_value": 79
    },
    "training_readiness": {
      "date": "2026-07-02",
      "score": 95,
      "level": "PRIME",
      "feedback_long": "PRIME_SS_HIGHEST_SS_AVAILABLE_ACWR_POS",
      "feedback_short": "PRIMED_AND_READY",
      "sleep_score_factor_percent": 95,
      "recovery_time_hours": 0,
      "hrv_factor_percent": 73,
      "stress_history_factor_percent": 76,
      "acwr_factor_percent": 100,
      "acute_load": 24
    },
    "training_status": {
      "date": "2026-07-02",
      "vo2_max": 40.0,
      "training_status": null,
      "load_balance_feedback": "AEROBIC_LOW_SHORTAGE"
    },
    "energy": {
      "date": "2026-07-02",
      "total_calories_burned": 1268.0,
      "bmr_calories": 1267.0,
      "active_calories": 1.0,
      "wellness_calories": 1268.0
    },
    "stress": {
      "date": "2026-07-02",
      "average_level": 17,
      "max_level": 90,
      "qualifier": "UNKNOWN",
      "rest_pct": 87.1,
      "low_pct": 7.13,
      "medium_pct": 4.18,
      "high_pct": 0.98
    },
    "intensity_minutes": {
      "date": "2026-07-02",
      "moderate_minutes": 0,
      "vigorous_minutes": 0,
      "weekly_goal": 150
    },
    "activity": {
      "date": "2026-07-02",
      "total_steps": 92,
      "step_goal": 5000,
      "highly_active_minutes": 2.0,
      "active_minutes": 1.0,
      "sedentary_minutes": 229.0,
      "floors_climbed": 0.0,
      "floors_goal": 10,
      "total_distance_meters": 75
    }
  },
  "rolling_7d": {
    "daily_signals": [
      {
        "date": "2026-06-26",
        "sleep_hours": 6.12,
        "sleep_score": 75,
        "hrv_last_night_avg": 35,
        "hrv_status": "BALANCED",
        "resting_heart_rate": 56,
        "total_calories_burned": 2718.0,
        "bmr_calories": 2239.0,
        "active_calories": 479.0,
        "steps": 5785,
        "stress_avg": 30,
        "stress_qualifier": "BALANCED",
        "moderate_intensity_minutes": 28,
        "vigorous_intensity_minutes": 15,
        "floors_climbed": 4.7956
      },
      {
        "date": "2026-06-27",
        "sleep_hours": 6.81,
        "sleep_score": 83,
        "hrv_last_night_avg": 46,
        "hrv_status": "BALANCED",
        "resting_heart_rate": 55,
        "total_calories_burned": 2466.0,
        "bmr_calories": 2237.0,
        "active_calories": 229.0,
        "steps": 5011,
        "stress_avg": 31,
        "stress_qualifier": "BALANCED",
        "moderate_intensity_minutes": 0,
        "vigorous_intensity_minutes": 0,
        "floors_climbed": 0.0
      },
      {
        "date": "2026-06-28",
        "sleep_hours": 9.41,
        "sleep_score": 74,
        "hrv_last_night_avg": 58,
        "hrv_status": "BALANCED",
        "resting_heart_rate": 54,
        "total_calories_burned": 2326.0,
        "bmr_calories": 2237.0,
        "active_calories": 89.0,
        "steps": 2616,
        "stress_avg": 27,
        "stress_qualifier": "BALANCED",
        "moderate_intensity_minutes": 0,
        "vigorous_intensity_minutes": 0,
        "floors_climbed": 0.0
      },
      {
        "date": "2026-06-29",
        "sleep_hours": 8.4,
        "sleep_score": 85,
        "hrv_last_night_avg": 47,
        "hrv_status": "BALANCED",
        "resting_heart_rate": 55,
        "total_calories_burned": 2341.0,
        "bmr_calories": 2239.0,
        "active_calories": 102.0,
        "steps": 3508,
        "stress_avg": 30,
        "stress_qualifier": "BALANCED",
        "moderate_intensity_minutes": 0,
        "vigorous_intensity_minutes": 0,
        "floors_climbed": 3.0
      },
      {
        "date": "2026-06-30",
        "sleep_hours": 8.25,
        "sleep_score": 81,
        "hrv_last_night_avg": 54,
        "hrv_status": "BALANCED",
        "resting_heart_rate": 54,
        "total_calories_burned": 2320.0,
        "bmr_calories": 2239.0,
        "active_calories": 81.0,
        "steps": 2674,
        "stress_avg": 34,
        "stress_qualifier": "BALANCED",
        "moderate_intensity_minutes": 0,
        "vigorous_intensity_minutes": 0,
        "floors_climbed": 0.0
      },
      {
        "date": "2026-07-01",
        "sleep_hours": 5.68,
        "sleep_score": 71,
        "hrv_last_night_avg": 46,
        "hrv_status": "BALANCED",
        "resting_heart_rate": 54,
        "total_calories_burned": 2374.0,
        "bmr_calories": 2239.0,
        "active_calories": 135.0,
        "steps": 3867,
        "stress_avg": 30,
        "stress_qualifier": "BALANCED",
        "moderate_intensity_minutes": 0,
        "vigorous_intensity_minutes": 0,
        "floors_climbed": 2.75787
      },
      {
        "date": "2026-07-02",
        "sleep_hours": 8.17,
        "sleep_score": 95,
        "hrv_last_night_avg": 51,
        "hrv_status": "BALANCED",
        "resting_heart_rate": 52,
        "total_calories_burned": 1268.0,
        "bmr_calories": 1267.0,
        "active_calories": 1.0,
        "steps": 92,
        "stress_avg": 17,
        "stress_qualifier": "UNKNOWN",
        "moderate_intensity_minutes": 0,
        "vigorous_intensity_minutes": 0,
        "floors_climbed": 0.0
      }
    ],
    "baselines": {
      "sleep_hours_7d_avg": 7.55,
      "sleep_score_7d_avg": 80.57,
      "hrv_7d_avg": 48.14,
      "rhr_7d_avg": 54.29,
      "steps_7d_avg": 3364.71,
      "total_calories_7d_avg": 2259.0,
      "active_calories_7d_avg": 159.43,
      "stress_7d_avg": 28.43
    }
  },
  "training_load": {
    "this_iso_week": {
      "window_start": "2026-06-29",
      "window_end": "2026-07-02",
      "activity_count": 0,
      "sum_activity_training_load": 0.0,
      "ok": true
    },
    "previous_iso_week": {
      "window_start": "2026-06-22",
      "window_end": "2026-06-28",
      "activity_count": 1,
      "sum_activity_training_load": 46.4,
      "ok": true
    },
    "acwr": {
      "date": "2026-07-02",
      "acwr_ratio": 0.2,
      "acwr_percent": 8,
      "acwr_status": "LOW",
      "acute_load": 24,
      "chronic_load": 100,
      "chronic_load_min": 80.0,
      "chronic_load_max": 150.0
    },
    "training_status": {
      "date": "2026-07-02",
      "training_status_numeric": 5,
      "training_status_label": "RECOVERY",
      "training_status_phrase": "RECOVERY_1"
    }
  },
  "weekly_summaries": {
    "weekly_intensity_minutes_4w": [
      {
        "week_starting": "2026-06-01",
        "moderate_minutes": null,
        "vigorous_minutes": null
      },
      {
        "week_starting": "2026-06-08",
        "moderate_minutes": null,
        "vigorous_minutes": null
      },
      {
        "week_starting": "2026-06-15",
        "moderate_minutes": null,
        "vigorous_minutes": null
      },
      {
        "week_starting": "2026-06-22",
        "moderate_minutes": null,
        "vigorous_minutes": null
      },
      {
        "week_starting": "2026-06-29",
        "moderate_minutes": null,
        "vigorous_minutes": null
      }
    ],
    "weekly_steps_4w": []
  },
  "body_composition": {
    "status": "ok",
    "most_recent": {
      "date": "2026-07-02",
      "timestamp_gmt": 1782997380000,
      "weight_lbs": 196.5,
      "bmi": 29.1,
      "body_fat_pct": 27.2,
      "body_water_pct": 50.1,
      "muscle_mass_lbs": 135.9,
      "bone_mass_lbs": 7.1,
      "visceral_fat": 4,
      "metabolic_age": 1104492410000.0,
      "physique_rating": null,
      "source": "INDEX_SCALE"
    },
    "trend_30d": [
      {
        "date": "2026-07-02",
        "timestamp_gmt": 1782997380000,
        "weight_lbs": 196.5,
        "bmi": 29.1,
        "body_fat_pct": 27.2,
        "body_water_pct": 50.1,
        "muscle_mass_lbs": 135.9,
        "bone_mass_lbs": 7.1,
        "visceral_fat": 4,
        "metabolic_age": 1104492410000.0,
        "physique_rating": null,
        "source": "INDEX_SCALE"
      },
      {
        "date": "2026-06-29",
        "timestamp_gmt": 1782741877000,
        "weight_lbs": 195.9,
        "bmi": 29.0,
        "body_fat_pct": 26.3,
        "body_water_pct": 50.3,
        "muscle_mass_lbs": 137.2,
        "bone_mass_lbs": 7.2,
        "visceral_fat": 3,
        "metabolic_age": 1072935484000.0,
        "physique_rating": null,
        "source": "INDEX_SCALE"
      },
      {
        "date": "2026-06-27",
        "timestamp_gmt": 1782571818000,
        "weight_lbs": 195.5,
        "bmi": 29.0,
        "body_fat_pct": 26.4,
        "body_water_pct": 50.0,
        "muscle_mass_lbs": 136.8,
        "bone_mass_lbs": 7.1,
        "visceral_fat": 3,
        "metabolic_age": 1104492410000.0,
        "physique_rating": null,
        "source": "INDEX_SCALE"
      },
      {
        "date": "2026-06-26",
        "timestamp_gmt": 1782506080000,
        "weight_lbs": 196.1,
        "bmi": 29.0,
        "body_fat_pct": 26.7,
        "body_water_pct": 49.8,
        "muscle_mass_lbs": 136.5,
        "bone_mass_lbs": 7.1,
        "visceral_fat": 3,
        "metabolic_age": 1104492410000.0,
        "physique_rating": null,
        "source": "INDEX_SCALE"
      },
      {
        "date": "2026-06-25",
        "timestamp_gmt": 1782392564000,
        "weight_lbs": 197.1,
        "bmi": 29.2,
        "body_fat_pct": 26.8,
        "body_water_pct": 49.7,
        "muscle_mass_lbs": 137.1,
        "bone_mass_lbs": 7.1,
        "visceral_fat": 3,
        "metabolic_age": 1104492410000.0,
        "physique_rating": null,
        "source": "INDEX_SCALE"
      },
      {
        "date": "2026-06-24",
        "timestamp_gmt": 1782303957000,
        "weight_lbs": 198.7,
        "bmi": 29.4,
        "body_fat_pct": 27.0,
        "body_water_pct": 49.6,
        "muscle_mass_lbs": 137.8,
        "bone_mass_lbs": 7.2,
        "visceral_fat": 3,
        "metabolic_age": 1104492410000.0,
        "physique_rating": null,
        "source": "INDEX_SCALE"
      },
      {
        "date": "2026-06-21",
        "timestamp_gmt": 1782050016000,
        "weight_lbs": 199.2,
        "bmi": 28.8,
        "body_fat_pct": 26.5,
        "body_water_pct": 50.3,
        "muscle_mass_lbs": 139.0,
        "bone_mass_lbs": 7.3,
        "visceral_fat": 3,
        "metabolic_age": 1104492410000.0,
        "physique_rating": null,
        "source": "INDEX_SCALE"
      },
      {
        "date": "2026-06-11",
        "timestamp_gmt": 1781183298000,
        "weight_lbs": 199.5,
        "bmi": 28.9,
        "body_fat_pct": 27.0,
        "body_water_pct": 49.5,
        "muscle_mass_lbs": 138.3,
        "bone_mass_lbs": 7.2,
        "visceral_fat": 4,
        "metabolic_age": 1104492410000.0,
        "physique_rating": null,
        "source": "INDEX_SCALE"
      },
      {
        "date": "2026-06-10",
        "timestamp_gmt": 1781093588000,
        "weight_lbs": 199.1,
        "bmi": 28.8,
        "body_fat_pct": 27.0,
        "body_water_pct": 49.7,
        "muscle_mass_lbs": 138.2,
        "bone_mass_lbs": 7.2,
        "visceral_fat": 3,
        "metabolic_age": 1104492410000.0,
        "physique_rating": null,
        "source": "INDEX_SCALE"
      },
      {
        "date": "2026-06-06",
        "timestamp_gmt": 1780761090000,
        "weight_lbs": 199.9,
        "bmi": 29.0,
        "body_fat_pct": 26.6,
        "body_water_pct": 50.3,
        "muscle_mass_lbs": 139.5,
        "bone_mass_lbs": 7.3,
        "visceral_fat": 3,
        "metabolic_age": 1104492410000.0,
        "physique_rating": null,
        "source": "INDEX_SCALE"
      }
    ],
    "weight_7d_avg_lbs": 197.0,
    "weight_7d_ago_lbs": 197.1,
    "weight_weekly_delta_lbs": -0.6,
    "weekly_delta_reason": null,
    "actual_rate_lb_per_wk": 0.6,
    "implied_actual_weekly_deficit_cal": 2100.0,
    "goal_weight_lbs": 165.0,
    "delta_to_goal_lbs": 31.5,
    "weeks_to_goal_at_2lb_per_week": 15.8
  },
  "workouts": [
    {
      "activity_id": 23385669400,
      "activity_name": "Pickleball",
      "activity_type": "pickleball",
      "start_time_local": "2026-06-26 08:08:57",
      "duration_minutes": 49.4,
      "calories": 375.0,
      "average_hr": 128.0,
      "max_hr": 162.0,
      "distance_meters": 655.1099853515625,
      "training_load": 46.4,
      "aerobic_training_effect": 2.799999952316284,
      "anaerobic_training_effect": 2.0,
      "steps": 2608,
      "body_battery_cost": -10,
      "hr_zone_1_seconds": 1009.0,
      "hr_zone_2_seconds": 161.0,
      "hr_zone_3_seconds": 6.0,
      "hr_zone_4_seconds": 0.0,
      "hr_zone_5_seconds": 0.0
    }
  ],
  "strength_detail": [],
  "exercise_trends": {
    "as_of": "2026-07-02",
    "window_days": 28,
    "lifts_tracked": 24,
    "recent_prs": [],
    "movers": []
  },
  "running_trends": {
    "as_of": "2026-07-02",
    "window_days": 28,
    "runs_4w": 0,
    "avg_pace_4w_min_km": null,
    "avg_pace_4w_fmt": null,
    "avg_pace_prev_4w_min_km": 8.58,
    "pace_delta_pct": null,
    "total_km_4w": 0,
    "best_pace_4w": null
  }
}